{"v":3,"stories":{"example-button--primary":{"id":"example-button--primary","title":"Example/Button","name":"Primary","importPath":"./.storybook/stories/Button.stories.js","tags":["story"],"kind":"Example/Button","story":"Primary","parameters":{"__id":"example-button--primary","docsOnly":false,"fileName":"./.storybook/stories/Button.stories.js"}},"example-button--secondary":{"id":"example-button--secondary","title":"Example/Button","name":"Secondary","importPath":"./.storybook/stories/Button.stories.js","tags":["story"],"kind":"Example/Button","story":"Secondary","parameters":{"__id":"example-button--secondary","docsOnly":false,"fileName":"./.storybook/stories/Button.stories.js"}}}}
